GazeML_keras/accuracy-92size100x100_Threshold_0.56.h5
GazeML_keras/diagnose.py
GazeML_keras/mtcnn_detect_face.py
GazeML_keras/detector/face_detector.py
GazeML_keras/mtcnn_weights/det1.npy
GazeML_keras/mtcnn_weights/det2.npy
GazeML_keras/mtcnn_weights/det3.npy
EyeDiagnosisLib-0.1.1.dist-info/LICENSE
EyeDiagnosisLib-0.1.1.dist-info/METADATA
EyeDiagnosisLib-0.1.1.dist-info/WHEEL
EyeDiagnosisLib-0.1.1.dist-info/top_level.txt
EyeDiagnosisLib-0.1.1.dist-info/RECORD
