Metadata-Version: 2.1
Name: EyeDiagnosisLib
Version: 0.1.1
Summary: Diagnose Cataracts Library
Home-page: UNKNOWN
Author: Khaldoun Alnaierat
Author-email: UNKNOWN
License: MIT
Platform: UNKNOWN
